triton/TEST_CONFIG_CLIENT.py
triton/__init__.py
triton/client.py
triton/config.py
triton/content_moderation.py
triton/context.py
triton/monitor.py
triton/pii.py
triton/pricing.py
triton/prompt.py
triton/py.typed
triton/token_extraction.py
triton/validation.py
triton_sdk-0.1.0.dist-info/METADATA
triton_sdk-0.1.0.dist-info/WHEEL
triton_sdk-0.1.0.dist-info/top_level.txt
triton_sdk-0.1.0.dist-info/RECORD
