Metadata-Version: 2.4
Name: triton-sdk
Version: 0.1.0
Summary: Enterprise-grade LLM middleware for monitoring and metadata tracking
Home-page: https://github.com/triton/sdk
Author: Triton Team
Author-email: Triton Team <team@triton.dev>
License: MIT
Project-URL: Homepage, https://github.com/triton/sdk
Project-URL: Documentation, https://docs.triton.dev
Project-URL: Repository, https://github.com/triton/sdk
Classifier: Development Status :: 3 - Alpha
Classifier: Intended Audience :: Developers
Classifier: Topic :: Software Development :: Libraries :: Python Modules
Classifier: License :: OSI Approved :: MIT License
Classifier: Programming Language :: Python :: 3
Classifier: Programming Language :: Python :: 3.11
Requires-Python: >=3.11
Requires-Dist: httpx>=0.26.0
Provides-Extra: dev
Requires-Dist: pytest>=7.4.0; extra == "dev"
Requires-Dist: pytest-asyncio>=0.21.0; extra == "dev"
Requires-Dist: black>=23.0.0; extra == "dev"
Requires-Dist: mypy>=1.0.0; extra == "dev"
Dynamic: author
Dynamic: home-page
Dynamic: requires-python
